autogenfiles/__init__.py
autogenfiles/__main__.py
autogenfiles/autogenfiles.py
autogenfiles/configuration.py
autogenfiles/files_helper.py
autogenfiles-0.0.4.dist-info/LICENSE
autogenfiles-0.0.4.dist-info/METADATA
autogenfiles-0.0.4.dist-info/WHEEL
autogenfiles-0.0.4.dist-info/entry_points.txt
autogenfiles-0.0.4.dist-info/top_level.txt
autogenfiles-0.0.4.dist-info/RECORD
