Metadata-Version: 2.1
Name: autogenfiles
Version: 0.0.4
Summary: Auto generate files based on a template
Home-page: http://github.com/jtemporal/autogenfiles
Author: Jessica Temporal
Author-email: hello@jtemporal.com
License: MIT
Keywords: auto generate files,jinja,templates,cli
Platform: UNKNOWN
Requires-Python: >=3.8.2
License-File: LICENSE
Requires-Dist: click (==8.0.1)
Requires-Dist: Jinja2 (==3.0.1)
